<?xml version="1.0" encoding="UTF-8"?>
<dictionary xmlns:xsi="http://www.w3.org/2001/XMLSchema-instance"
xsi:noNamespaceSchemaLocation="english_chinese.xsd">

<word id="5047" name="ji&#462;">
<source name="english">fake , false , artificial , to borrow , if , suppose</source>
<target name="chinese">
<dialect name="mandarin">
<pronunciation>ji&#462;</pronunciation>
<characters style="simplified">假</characters>
</dialect>

<!-- <dialect name="cantonese">
<pronunciation>ji&#462;</pronunciation>
<characters style="simplified">same</characters>
</dialect> -->

</target>
<url>
<gif src="resources/img/5047.gif" />
<audio src="resources/audio/5047.wav" />
</url>
</word>
</dictionary>