<?xml version="1.0" encoding="UTF-8"?>
<dictionary xmlns:xsi="http://www.w3.org/2001/XMLSchema-instance"
xsi:noNamespaceSchemaLocation="english_chinese.xsd">

<word id="5361" name="k&#462;">
<source name="english">to check , to stop , to block , card</source>
<target name="chinese">
<dialect name="mandarin">
<pronunciation>k&#462;</pronunciation>
<characters style="simplified">卡</characters>
</dialect>

<!-- <dialect name="cantonese">
<pronunciation>k&#462;</pronunciation>
<characters style="simplified">same</characters>
</dialect> -->

</target>
<url>
<gif src="resources/img/5361.gif" />
<audio src="resources/audio/5361.wav" />
</url>
</word>
</dictionary>