<?xml version="1.0" encoding="UTF-8"?>
<dictionary xmlns:xsi="http://www.w3.org/2001/XMLSchema-instance"
xsi:noNamespaceSchemaLocation="english_chinese.xsd">

<word id="5f8a" name="hu&#225;i">
<source name="english">irresolute , move back and forth</source>
<target name="chinese">
<dialect name="mandarin">
<pronunciation>hu&#225;i</pronunciation>
<characters style="simplified">徊</characters>
</dialect>

<!-- <dialect name="cantonese">
<pronunciation>hu&#225;i</pronunciation>
<characters style="simplified">same</characters>
</dialect> -->

</target>
<url>
<gif src="resources/img/5f8a.gif" />
<audio src="resources/audio/5f8a.wav" />
</url>
</word>
</dictionary>