<?xml version="1.0" encoding="UTF-8"?>
<dictionary xmlns:xsi="http://www.w3.org/2001/XMLSchema-instance"
xsi:noNamespaceSchemaLocation="english_chinese.xsd">

<word id="607c" name="n&#462;o">
<source name="english">get mad</source>
<target name="chinese">
<dialect name="mandarin">
<pronunciation>n&#462;o</pronunciation>
<characters style="simplified">恼</characters>
</dialect>

<!-- <dialect name="cantonese">
<pronunciation>n&#462;o</pronunciation>
<characters style="simplified">惱</characters>
</dialect> -->

</target>
<url>
<gif src="resources/img/607c.gif" />
<audio src="resources/audio/607c.wav" />
</url>
</word>
</dictionary>