<?xml version="1.0" encoding="UTF-8"?>
<dictionary xmlns:xsi="http://www.w3.org/2001/XMLSchema-instance"
xsi:noNamespaceSchemaLocation="english_chinese.xsd">

<word id="6f0f" name="l&#242;u">
<source name="english">funnel , to leak , to let out , to divulge</source>
<target name="chinese">
<dialect name="mandarin">
<pronunciation>l&#242;u</pronunciation>
<characters style="simplified">漏</characters>
</dialect>

<!-- <dialect name="cantonese">
<pronunciation>l&#242;u</pronunciation>
<characters style="simplified">same</characters>
</dialect> -->

</target>
<url>
<gif src="resources/img/6f0f.gif" />
<audio src="resources/audio/6f0f.wav" />
</url>
</word>
</dictionary>