<?xml version="1.0" encoding="UTF-8"?>
<dictionary xmlns:xsi="http://www.w3.org/2001/XMLSchema-instance"
xsi:noNamespaceSchemaLocation="english_chinese.xsd">

<word id="797a" name="q&#237;">
<source name="english">felicity</source>
<target name="chinese">
<dialect name="mandarin">
<pronunciation>q&#237;</pronunciation>
<characters style="simplified">祺</characters>
</dialect>

<!-- <dialect name="cantonese">
<pronunciation>q&#237;</pronunciation>
<characters style="simplified">same</characters>
</dialect> -->

</target>
<url>
<gif src="resources/img/797a.gif" />
<audio src="resources/audio/797a.wav" />
</url>
</word>
</dictionary>